{"name":"User enters invalid card information","id":"make-payment-with-debit-or-credit-card;user-enters-invalid-card-information","scenarioId":"post_pay_with_card:User enters invalid card information","methodName":"User enters invalid card information","testSteps":[{"number":1,"description":"Given The user is on the payment page","duration":238,"startTime":"2024-11-25T21:19:57.626129700-05:00[America/Bogota]","result":"SUCCESS","precondition":false,"level":0,"children":[{"number":2,"description":"Actor navigate to","duration":172,"startTime":"2024-11-25T21:19:57.631128200-05:00[America/Bogota]","result":"SUCCESS","precondition":false,"level":1,"children":[{"number":3,"description":"actor opens the browser at https://code-factory-presencial-front-my1l6zi9a.vercel.app","duration":162,"startTime":"2024-11-25T21:19:57.635129-05:00[America/Bogota]","result":"SUCCESS","precondition":false,"level":2}]},{"number":4,"description":"Then parameter to validate should be (true)","duration":8,"startTime":"2024-11-25T21:19:57.849550900-05:00[America/Bogota]","result":"SUCCESS","precondition":false,"level":1}]},{"number":5,"description":"When The user selects the option to pay with a credit card or debit card","duration":444,"startTime":"2024-11-25T21:19:57.865544800-05:00[America/Bogota]","result":"SUCCESS","precondition":false,"level":0,"children":[{"number":6,"description":"Actor find the","duration":253,"startTime":"2024-11-25T21:19:57.868554600-05:00[America/Bogota]","result":"SUCCESS","precondition":false,"level":1,"children":[{"number":7,"description":"Actor click element","duration":242,"startTime":"2024-11-25T21:19:57.874547600-05:00[America/Bogota]","result":"SUCCESS","precondition":false,"level":2,"children":[{"number":8,"description":"actor clicks on Payment method","duration":229,"startTime":"2024-11-25T21:19:57.880549300-05:00[America/Bogota]","result":"SUCCESS","precondition":false,"level":3}]}]},{"number":9,"description":"Actor find the","duration":176,"startTime":"2024-11-25T21:19:58.126731500-05:00[America/Bogota]","result":"SUCCESS","precondition":false,"level":1,"children":[{"number":10,"description":"Actor click element","duration":168,"startTime":"2024-11-25T21:19:58.130729600-05:00[America/Bogota]","result":"SUCCESS","precondition":false,"level":2,"children":[{"number":11,"description":"actor clicks on Continue button","duration":158,"startTime":"2024-11-25T21:19:58.133745500-05:00[America/Bogota]","result":"SUCCESS","precondition":false,"level":3}]}]}]},{"number":12,"description":"And The user provides invalid card information (invalid card number, expired expiration date, incorrect CVV)","duration":1075,"startTime":"2024-11-25T21:19:58.309728600-05:00[America/Bogota]","result":"SUCCESS","precondition":false,"level":0,"children":[{"number":13,"description":"Actor provide card details","duration":910,"startTime":"2024-11-25T21:19:58.312732-05:00[America/Bogota]","result":"SUCCESS","precondition":false,"level":1,"children":[{"number":14,"description":"Actor enter value","duration":146,"startTime":"2024-11-25T21:19:58.322736-05:00[America/Bogota]","result":"SUCCESS","precondition":false,"level":2,"children":[{"number":15,"description":"actor enters \u0027John Doe\u0027 into Card holder name input","duration":135,"startTime":"2024-11-25T21:19:58.326738300-05:00[America/Bogota]","result":"SUCCESS","precondition":false,"level":3}]},{"number":16,"description":"Actor enter value","duration":137,"startTime":"2024-11-25T21:19:58.468753200-05:00[America/Bogota]","result":"SUCCESS","precondition":false,"level":2,"children":[{"number":17,"description":"actor enters \u0027123423456\u0027 into Card number input","duration":130,"startTime":"2024-11-25T21:19:58.471756500-05:00[America/Bogota]","result":"SUCCESS","precondition":false,"level":3}]},{"number":18,"description":"Actor click element","duration":146,"startTime":"2024-11-25T21:19:58.607683400-05:00[America/Bogota]","result":"SUCCESS","precondition":false,"level":2,"children":[{"number":19,"description":"actor clicks on Card expiration month input","duration":138,"startTime":"2024-11-25T21:19:58.610707400-05:00[America/Bogota]","result":"SUCCESS","precondition":false,"level":3}]},{"number":20,"description":"actor selects [Ljava.lang.String;@14b95942 in Card expiration month input","duration":93,"startTime":"2024-11-25T21:19:58.756597400-05:00[America/Bogota]","result":"SUCCESS","precondition":false,"level":2},{"number":21,"description":"Actor click element","duration":143,"startTime":"2024-11-25T21:19:58.850849100-05:00[America/Bogota]","result":"SUCCESS","precondition":false,"level":2,"children":[{"number":22,"description":"actor clicks on Card expiration year input","duration":133,"startTime":"2024-11-25T21:19:58.854854400-05:00[America/Bogota]","result":"SUCCESS","precondition":false,"level":3}]},{"number":23,"description":"actor selects [Ljava.lang.String;@45d389f2 in Card expiration year input","duration":87,"startTime":"2024-11-25T21:19:58.996253200-05:00[America/Bogota]","result":"SUCCESS","precondition":false,"level":2},{"number":24,"description":"Actor enter value","duration":132,"startTime":"2024-11-25T21:19:59.084455200-05:00[America/Bogota]","result":"SUCCESS","precondition":false,"level":2,"children":[{"number":25,"description":"actor enters \u002777784\u0027 into Card security code input","duration":123,"startTime":"2024-11-25T21:19:59.089456400-05:00[America/Bogota]","result":"SUCCESS","precondition":false,"level":3}]}]},{"number":26,"description":"Actor find the","duration":151,"startTime":"2024-11-25T21:19:59.228064200-05:00[America/Bogota]","result":"SUCCESS","precondition":false,"level":1,"children":[{"number":27,"description":"Actor click element","duration":140,"startTime":"2024-11-25T21:19:59.232056-05:00[America/Bogota]","result":"SUCCESS","precondition":false,"level":2,"children":[{"number":28,"description":"actor clicks on Confirm purchase button","duration":119,"startTime":"2024-11-25T21:19:59.235064300-05:00[America/Bogota]","result":"SUCCESS","precondition":false,"level":3}]}]}]},{"number":29,"description":"Then The user sees an error message indicating that the provided information is invalid","duration":2411,"startTime":"2024-11-25T21:19:59.385032300-05:00[America/Bogota]","result":"FAILURE","precondition":false,"level":0,"children":[{"number":30,"description":"Then parameter to validate should be (true)","duration":372,"startTime":"2024-11-25T21:20:01.405500900-05:00[America/Bogota]","screenshots":[{"screenshot":"f83029ff37fb2e85bdc7294b185aa47fad35c746600b106dee4edc5ba4847787.png","htmlSource":"pagesource1683891280107388925.html","timeStamp":1732587601773,"screenshotName":"f83029ff37fb2e85bdc7294b185aa47fad35c746600b106dee4edc5ba4847787.png"}],"exception":{"errorType":"java.lang.AssertionError","message":"\nExpected: is \u003ctrue\u003e\n     but: was \u003cfalse\u003e","stackTrace":[{"declaringClass":"co.com.udea.pagosb.modulopagosb.stepdefinitions.PostPayWithCardStepDefinitions","methodName":"theUserSeesAnErrorMessageIndicatingThatTheProvidedInformationIsInvalid","fileName":"PostPayWithCardStepDefinitions.java","lineNumber":96},{"declaringClass":"worker.org.gradle.process.internal.worker.GradleWorkerMain","methodName":"run","fileName":"GradleWorkerMain.java","lineNumber":69},{"declaringClass":"worker.org.gradle.process.internal.worker.GradleWorkerMain","methodName":"main","fileName":"GradleWorkerMain.java","lineNumber":74}]},"result":"FAILURE","precondition":false,"level":1}]}],"userStory":{"id":"post_pay_with_card","storyName":"Make payment with debit or credit card","displayName":"Make payment with debit or credit card","path":"post_pay_with_card","pathElements":[{"name":"post_pay_with_card","description":""}],"type":"feature"},"title":"User enters invalid card information","description":"","tags":[{"name":"Chrome","type":"context","displayName":"Chrome"},{"name":"Windows","type":"context","displayName":"Windows"},{"name":"Chrome, Windows","type":"context","displayName":"Chrome, Windows"}],"startTime":"2024-11-25T21:19:57.567125700-05:00[America/Bogota]","duration":228,"testFailureCause":{"errorType":"java.lang.AssertionError","message":"\nExpected: is \u003ctrue\u003e\n     but: was \u003cfalse\u003e","stackTrace":[{"declaringClass":"co.com.udea.pagosb.modulopagosb.stepdefinitions.PostPayWithCardStepDefinitions","methodName":"theUserSeesAnErrorMessageIndicatingThatTheProvidedInformationIsInvalid","fileName":"PostPayWithCardStepDefinitions.java","lineNumber":96},{"declaringClass":"worker.org.gradle.process.internal.worker.GradleWorkerMain","methodName":"run","fileName":"GradleWorkerMain.java","lineNumber":69},{"declaringClass":"worker.org.gradle.process.internal.worker.GradleWorkerMain","methodName":"main","fileName":"GradleWorkerMain.java","lineNumber":74}]},"testFailureClassname":"java.lang.AssertionError","testFailureMessage":"\nExpected: is \u003ctrue\u003e\n     but: was \u003cfalse\u003e","testFailureSummary":"FAILURE;java.lang.AssertionError;\nExpected: is \u003ctrue\u003e\n     but: was \u003cfalse\u003e;PostPayWithCardStepDefinitions.java","projectKey":"","annotatedResult":"FAILURE","sessionId":"d6c5332778ea7e66800edebe84a2017a","driver":"chrome:actor","isManualTestingUpToDate":false,"context":"chrome,windows","manual":false,"testSource":"Cucumber","actors":[{"name":"actor","can":["browse the web"]},{"name":"user","can":["browse the web"]}],"order":0,"result":"FAILURE"}