{"name":"User completes the transaction using a credit card or debit card","id":"make-payment-with-debit-or-credit-card;user-completes-the-transaction-using-a-credit-card-or-debit-card","scenarioId":"post_pay_with_card:User completes the transaction using a credit card or debit card","methodName":"User completes the transaction using a credit card or debit card","testSteps":[{"number":1,"description":"Given The user is on the payment page","duration":9393,"startTime":"2024-11-24T13:28:36.600327100-05:00[America/Bogota]","result":"SUCCESS","precondition":false,"level":0,"children":[{"number":2,"description":"Actor navigate to","duration":8560,"startTime":"2024-11-24T13:28:36.925327500-05:00[America/Bogota]","result":"SUCCESS","precondition":false,"level":1,"children":[{"number":3,"description":"actor opens the browser at https://code-factory-presencial-front-k9i7rb30g.vercel.app","duration":8528,"startTime":"2024-11-24T13:28:36.946355200-05:00[America/Bogota]","result":"SUCCESS","precondition":false,"level":2}]},{"number":4,"description":"Then parameter to validate should be (true)","duration":12,"startTime":"2024-11-24T13:28:45.973090-05:00[America/Bogota]","result":"SUCCESS","precondition":false,"level":1}]},{"number":5,"description":"When The user selects the option to pay with a credit card or debit card","duration":615,"startTime":"2024-11-24T13:28:45.995092400-05:00[America/Bogota]","result":"SUCCESS","precondition":false,"level":0,"children":[{"number":6,"description":"Actor find the","duration":322,"startTime":"2024-11-24T13:28:46.016093-05:00[America/Bogota]","result":"SUCCESS","precondition":false,"level":1,"children":[{"number":7,"description":"Actor click element","duration":292,"startTime":"2024-11-24T13:28:46.037086300-05:00[America/Bogota]","result":"SUCCESS","precondition":false,"level":2,"children":[{"number":8,"description":"actor clicks on Payment method","duration":265,"startTime":"2024-11-24T13:28:46.057089300-05:00[America/Bogota]","result":"SUCCESS","precondition":false,"level":3}]}]},{"number":9,"description":"Actor find the","duration":255,"startTime":"2024-11-24T13:28:46.348312500-05:00[America/Bogota]","result":"SUCCESS","precondition":false,"level":1,"children":[{"number":10,"description":"Actor click element","duration":240,"startTime":"2024-11-24T13:28:46.353312400-05:00[America/Bogota]","result":"SUCCESS","precondition":false,"level":2,"children":[{"number":11,"description":"actor clicks on Continue button","duration":227,"startTime":"2024-11-24T13:28:46.360313-05:00[America/Bogota]","result":"SUCCESS","precondition":false,"level":3}]}]}]},{"number":12,"description":"And The user provides the card details (card number, expiration date, CVV)","duration":1223,"startTime":"2024-11-24T13:28:46.612353700-05:00[America/Bogota]","result":"SUCCESS","precondition":false,"level":0,"children":[{"number":13,"description":"Actor provide card details","duration":1163,"startTime":"2024-11-24T13:28:46.667346900-05:00[America/Bogota]","result":"SUCCESS","precondition":false,"level":1,"children":[{"number":14,"description":"Actor enter value","duration":213,"startTime":"2024-11-24T13:28:46.708338-05:00[America/Bogota]","result":"SUCCESS","precondition":false,"level":2,"children":[{"number":15,"description":"actor enters \u0027John Doe\u0027 into Card holder name input","duration":182,"startTime":"2024-11-24T13:28:46.733345-05:00[America/Bogota]","result":"SUCCESS","precondition":false,"level":3}]},{"number":16,"description":"Actor enter value","duration":175,"startTime":"2024-11-24T13:28:46.923329200-05:00[America/Bogota]","result":"SUCCESS","precondition":false,"level":2,"children":[{"number":17,"description":"actor enters \u00271234567890123456\u0027 into Card number input","duration":165,"startTime":"2024-11-24T13:28:46.928321700-05:00[America/Bogota]","result":"SUCCESS","precondition":false,"level":3}]},{"number":18,"description":"Actor click element","duration":184,"startTime":"2024-11-24T13:28:47.099692100-05:00[America/Bogota]","result":"SUCCESS","precondition":false,"level":2,"children":[{"number":19,"description":"actor clicks on Card expiration month input","duration":172,"startTime":"2024-11-24T13:28:47.103674600-05:00[America/Bogota]","result":"SUCCESS","precondition":false,"level":3}]},{"number":20,"description":"actor selects [Ljava.lang.String;@35fa450f in Card expiration month input","duration":135,"startTime":"2024-11-24T13:28:47.295660300-05:00[America/Bogota]","result":"SUCCESS","precondition":false,"level":2},{"number":21,"description":"Actor click element","duration":158,"startTime":"2024-11-24T13:28:47.431665900-05:00[America/Bogota]","result":"SUCCESS","precondition":false,"level":2,"children":[{"number":22,"description":"actor clicks on Card expiration year input","duration":147,"startTime":"2024-11-24T13:28:47.437660700-05:00[America/Bogota]","result":"SUCCESS","precondition":false,"level":3}]},{"number":23,"description":"actor selects [Ljava.lang.String;@267891bf in Card expiration year input","duration":99,"startTime":"2024-11-24T13:28:47.592663300-05:00[America/Bogota]","result":"SUCCESS","precondition":false,"level":2},{"number":24,"description":"Actor enter value","duration":131,"startTime":"2024-11-24T13:28:47.693552800-05:00[America/Bogota]","result":"SUCCESS","precondition":false,"level":2,"children":[{"number":25,"description":"actor enters \u0027777\u0027 into Card security code input","duration":121,"startTime":"2024-11-24T13:28:47.697555800-05:00[America/Bogota]","result":"SUCCESS","precondition":false,"level":3}]}]}]},{"number":26,"description":"Then The transaction is completed successfully","duration":173,"startTime":"2024-11-24T13:28:47.836582800-05:00[America/Bogota]","result":"SUCCESS","precondition":false,"level":0,"children":[{"number":27,"description":"Actor find the","duration":164,"startTime":"2024-11-24T13:28:47.840217-05:00[America/Bogota]","result":"SUCCESS","precondition":false,"level":1,"children":[{"number":28,"description":"Actor click element","duration":156,"startTime":"2024-11-24T13:28:47.843217100-05:00[America/Bogota]","result":"SUCCESS","precondition":false,"level":2,"children":[{"number":29,"description":"actor clicks on Confirm purchase button","duration":145,"startTime":"2024-11-24T13:28:47.848218400-05:00[America/Bogota]","result":"SUCCESS","precondition":false,"level":3}]}]}]},{"number":30,"description":"And The user sees a payment confirmation message","duration":128,"startTime":"2024-11-24T13:28:48.010991800-05:00[America/Bogota]","result":"SUCCESS","precondition":false,"level":0,"children":[{"number":31,"description":"Then parameter to validate should be (true)","duration":6,"startTime":"2024-11-24T13:28:48.124466-05:00[America/Bogota]","result":"SUCCESS","precondition":false,"level":1}]}],"userStory":{"id":"post_pay_with_card","storyName":"Make payment with debit or credit card","displayName":"Make payment with debit or credit card","path":"post_pay_with_card","pathElements":[{"name":"post_pay_with_card","description":""}],"type":"feature"},"title":"User completes the transaction using a credit card or debit card","description":"","tags":[{"name":"Chrome","type":"context","displayName":"Chrome"},{"name":"Windows","type":"context","displayName":"Windows"},{"name":"Chrome, Windows","type":"context","displayName":"Chrome, Windows"}],"startTime":"2024-11-24T13:28:36.332338400-05:00[America/Bogota]","duration":9126,"projectKey":"","sessionId":"418d7764ec531827cf250e59cf9c85e1","driver":"chrome:actor","isManualTestingUpToDate":false,"context":"chrome,windows","manual":false,"testSource":"Cucumber","actors":[{"name":"actor","can":["browse the web"]},{"name":"user","can":["browse the web"]}],"order":0,"result":"SUCCESS"}